lhub_extractors/__init__.py
lhub_extractors/decorators.py
lhub_extractors/generate_metadata.py
lhub_extractors/params.py
lhub_extractors/shim_exec.py
lhub_extractors/util.py
lhub_extractors-0.4.0.dist-info/WHEEL
lhub_extractors-0.4.0.dist-info/METADATA
lhub_extractors-0.4.0.dist-info/RECORD
