Metadata-Version: 2.1
Name: lhub-extractors
Version: 0.4.0
Summary: LogicHub Feature Extractors
Author: Bernie Liu
Author-email: bernie@logichub.com
Requires-Python: >=3.6
Classifier: Programming Language :: Python :: 3
Classifier: Programming Language :: Python :: 3.6
Classifier: Programming Language :: Python :: 3.7
Requires-Dist: click (>=7.0,<7.1)
Requires-Dist: dataclasses-json
Requires-Dist: docstring-parser (>=0.1,<0.2)
Requires-Dist: wheel (>=0.32.3,<0.33.0)
